spreado/__init__.py
spreado/__main__.py
spreado/__version__.py
spreado/conf.py
spreado/cli/__init__.py
spreado/cli/cli.py
spreado/cookies/douyin_uploader/account.json
spreado/cookies/kuaishou_uploader/account.json
spreado/cookies/shipinhao_uploader/account.json
spreado/cookies/xiaohongshu_uploader/account.json
spreado/examples/get_douyin_cookie.py
spreado/examples/get_kuaishou_cookie.py
spreado/examples/get_shipinhao_cookie.py
spreado/examples/get_xiaohongshu_cookie.py
spreado/examples/upload_video_to_douyin.py
spreado/examples/upload_video_to_kuaishou.py
spreado/examples/upload_video_to_shipinhao.py
spreado/examples/upload_video_to_xiaohongshu.py
spreado/publisher/__init__.py
spreado/publisher/browser.py
spreado/publisher/uploader.py
spreado/publisher/douyin_uploader/__init__.py
spreado/publisher/douyin_uploader/uploader.py
spreado/publisher/kuaishou_uploader/__init__.py
spreado/publisher/kuaishou_uploader/uploader.py
spreado/publisher/shipinhao_uploader/__init__.py
spreado/publisher/shipinhao_uploader/uploader.py
spreado/publisher/xiaohongshu_uploader/__init__.py
spreado/publisher/xiaohongshu_uploader/uploader.py
spreado/utils/__init__.py
spreado/utils/files_times.py
spreado/utils/log.py
spreado-1.0.1.dist-info/METADATA
spreado-1.0.1.dist-info/WHEEL
spreado-1.0.1.dist-info/entry_points.txt
spreado-1.0.1.dist-info/top_level.txt
spreado-1.0.1.dist-info/RECORD
