Metadata-Version: 2.4
Name: spreado
Version: 1.0.1
Summary: 全平台内容发布工具 - 支持抖音、小红书、快手、视频号等平台
Home-page: https://github.com/yourname/spreado
Author: Your Name
Author-email: wangruiyu <wry10150@163.com>
License-Expression: MIT
Project-URL: Homepage, https://github.com/yourname/spreado
Project-URL: Repository, https://github.com/yourname/spreado
Project-URL: Issues, https://github.com/yourname/spreado/issues
Keywords: video,upload,automation,social-media,douyin,xiaohongshu,kuaishou
Classifier: Development Status :: 4 - Beta
Classifier: Intended Audience :: Developers
Classifier: Operating System :: OS Independent
Classifier: Programming Language :: Python :: 3
Classifier: Programming Language :: Python :: 3.8
Classifier: Programming Language :: Python :: 3.9
Classifier: Programming Language :: Python :: 3.10
Classifier: Programming Language :: Python :: 3.11
Classifier: Programming Language :: Python :: 3.12
Requires-Python: >=3.8
Requires-Dist: playwright>=1.40.0
Requires-Dist: playwright-stealth>=2.0.1
Requires-Dist: loguru>=0.7.0
Requires-Dist: pytz>=2024.1
Requires-Dist: typing-extensions>=4.9.0
Requires-Dist: pyee>=11.0.0
Provides-Extra: dev
Requires-Dist: pytest>=7.4.0; extra == "dev"
Requires-Dist: black>=23.0.0; extra == "dev"
Requires-Dist: ruff>=0.1.0; extra == "dev"
Dynamic: author
Dynamic: home-page
Dynamic: requires-python
